pyams_alchemy/__init__.py
pyams_alchemy/engine.py
pyams_alchemy/include.py
pyams_alchemy/interfaces.py
pyams_alchemy/loader.py
pyams_alchemy/manager.py
pyams_alchemy/monitor.py
pyams_alchemy/schema.py
pyams_alchemy/converter/__init__.py
pyams_alchemy/converter/csv.py
pyams_alchemy/converter/json.py
pyams_alchemy/doctests/README.rst
pyams_alchemy/generations/__init__.py
pyams_alchemy/locales/pyams_alchemy.pot
pyams_alchemy/locales/fr/LC_MESSAGES/pyams_alchemy.mo
pyams_alchemy/locales/fr/LC_MESSAGES/pyams_alchemy.po
pyams_alchemy/task/__init__.py
pyams_alchemy/task/interfaces.py
pyams_alchemy/task/zmi/__init__.py
pyams_alchemy/tests/__init__.py
pyams_alchemy/tests/test_utilsdocs.py
pyams_alchemy/tests/test_utilsdocstrings.py
pyams_alchemy/zmi/__init__.py
pyams_alchemy/zmi/engine.py
pyams_alchemy/zmi/test.py
pyams_alchemy-2.4.0.dist-info/LICENSE
pyams_alchemy-2.4.0.dist-info/METADATA
pyams_alchemy-2.4.0.dist-info/WHEEL
pyams_alchemy-2.4.0.dist-info/namespace_packages.txt
pyams_alchemy-2.4.0.dist-info/top_level.txt
pyams_alchemy-2.4.0.dist-info/RECORD
