Metadata-Version: 2.1
Name: pyams-alchemy
Version: 2.4.0
Summary: PyAMS SQLAlchemy extension
Home-page: https://pyams.readthedocs.io
Author: Thierry Florac
Author-email: tflorac@ulthar.net
License: ZPL
Keywords: Pyramid PyAMS
Classifier: License :: OSI Approved :: Zope Public License
Classifier: Development Status :: 4 - Beta
Classifier: Programming Language :: Python
Classifier: Framework :: Pyramid
Classifier: Topic :: Software Development :: Libraries :: Python Modules
License-File: LICENSE
Requires-Dist: setuptools
Requires-Dist: persistent
Requires-Dist: pyams-security
Requires-Dist: pyams-site
Requires-Dist: pyams-utils >=2.8.0
Requires-Dist: pyramid >=2.0.0
Requires-Dist: sqlalchemy
Requires-Dist: zope.annotation
Requires-Dist: zope.componentvocabulary
Requires-Dist: zope.container
Requires-Dist: zope.copy
Requires-Dist: zope.interface
Requires-Dist: zope.intid
Requires-Dist: zope.lifecycleevent
Requires-Dist: zope.schema
Requires-Dist: zope.sqlalchemy
Provides-Extra: test
Requires-Dist: pyams-scheduler >=2.7.0 ; extra == 'test'
Requires-Dist: pyams-zmi ; extra == 'test'
Requires-Dist: pyramid-zcml ; extra == 'test'
Requires-Dist: zope.exceptions ; extra == 'test'
